maskurl/__init__.py
maskurl/maskurl.py
maskurl-1.0.1.dist-info/METADATA
maskurl-1.0.1.dist-info/WHEEL
maskurl-1.0.1.dist-info/entry_points.txt
maskurl-1.0.1.dist-info/top_level.txt
maskurl-1.0.1.dist-info/RECORD
